{
    "total_orders": 417,
    "orders_delivered": 107,
    "total_delay": 0,
    "late_orders": [
        0,
        2,
        3,
        5,
        6,
        7,
        9,
        10,
        11,
        13,
        14,
        15,
        16,
        17,
        18,
        19,
        20,
        21,
        22,
        23,
        24,
        25,
        26,
        27,
        28,
        29,
        30,
        31,
        32,
        33,
        34,
        35,
        36,
        37,
        38,
        39,
        40,
        41,
        42,
        43,
        44,
        45,
        46,
        47,
        48,
        49,
        50,
        51,
        52,
        53,
        54,
        55,
        56,
        57,
        58,
        59,
        60,
        61,
        62,
        63,
        64,
        65,
        66,
        67,
        68,
        69,
        70,
        71,
        72,
        73,
        74,
        75,
        76,
        77,
        78,
        79,
        80,
        81,
        82,
        83,
        85,
        86,
        87,
        88,
        89,
        91,
        92,
        93,
        94,
        95,
        96,
        97,
        98,
        100,
        102,
        103,
        106,
        111,
        116,
        120,
        122,
        139,
        140
    ],
    "max_delay": 274,
    "delay_values": [
        6,
        12,
        2,
        6,
        6,
        14,
        13,
        17,
        9,
        10,
        30,
        19,
        27,
        28,
        26,
        31,
        40,
        37,
        44,
        39,
        51,
        40,
        61,
        51,
        58,
        75,
        72,
        52,
        81,
        67,
        71,
        82,
        86,
        82,
        96,
        98,
        104,
        84,
        97,
        94,
        100,
        70,
        100,
        118,
        93,
        111,
        120,
        123,
        109,
        115,
        123,
        141,
        140,
        151,
        137,
        134,
        133,
        149,
        158,
        155,
        157,
        141,
        158,
        173,
        160,
        166,
        153,
        147,
        190,
        190,
        172,
        168,
        186,
        144,
        186,
        197,
        219,
        189,
        207,
        192,
        213,
        218,
        231,
        216,
        166,
        214,
        220,
        230,
        222,
        225,
        228,
        245,
        252,
        194,
        215,
        274,
        260,
        241,
        251,
        240,
        258,
        270,
        273
    ],
    "total_distance": 86690.79858721557,
    "postponed_orders": [
        1,
        2,
        3,
        4,
        5,
        6,
        7,
        8,
        9,
        10,
        11,
        12,
        13,
        15,
        16,
        17,
        18,
        19,
        20,
        21,
        22,
        23,
        24,
        25,
        26,
        27,
        28,
        29,
        30,
        31,
        32,
        33,
        34,
        35,
        36,
        37,
        38,
        39,
        40,
        41,
        42,
        43,
        44,
        45,
        46,
        47,
        48,
        49,
        50,
        51,
        52,
        53,
        54,
        55,
        56,
        57,
        58,
        59,
        60,
        61,
        62,
        63,
        64,
        65,
        66,
        67,
        68,
        69,
        70,
        71,
        72,
        73,
        74,
        75,
        76,
        77,
        78,
        79,
        80,
        81,
        82,
        83,
        84,
        85,
        86,
        87,
        89,
        90,
        91,
        92,
        93,
        94,
        95,
        96,
        97,
        98,
        99,
        100,
        101,
        102,
        103,
        104,
        105,
        106,
        107,
        108,
        109,
        110,
        111,
        112,
        113,
        114,
        115,
        116,
        117,
        118,
        119,
        120,
        121,
        122,
        123,
        124,
        125,
        126,
        127,
        128,
        129,
        130,
        131,
        132,
        133,
        134,
        135,
        136,
        137,
        138,
        139,
        140,
        141,
        142,
        143,
        144,
        145,
        146,
        147,
        148,
        149,
        150,
        151,
        152,
        153,
        154,
        155,
        156,
        157,
        158,
        159,
        160,
        161,
        162,
        163,
        164,
        165,
        166,
        167,
        168,
        169,
        170,
        171,
        172,
        173,
        174,
        175,
        176,
        177,
        178,
        179,
        180,
        181,
        182,
        183,
        184,
        185,
        186,
        187,
        188,
        189,
        190,
        191,
        192,
        193,
        194,
        195,
        196,
        197,
        198,
        199,
        200,
        201,
        202,
        203,
        204,
        205,
        206,
        207,
        208,
        209,
        210,
        211,
        212,
        213,
        214,
        215,
        216,
        217,
        218,
        219,
        220,
        221,
        222,
        223,
        224,
        225,
        226,
        227,
        228,
        229,
        230,
        231,
        232,
        233,
        234,
        235,
        236,
        237,
        238,
        239,
        240,
        241,
        242,
        243,
        244,
        245,
        246,
        247,
        248,
        249,
        250,
        251,
        252,
        253,
        254,
        255,
        256,
        257,
        258,
        259,
        260,
        261,
        262,
        263,
        264,
        265,
        266,
        267,
        268,
        269,
        270,
        271,
        272,
        273,
        274,
        275,
        276,
        277,
        278,
        279,
        280,
        281,
        282,
        283,
        284,
        285,
        286,
        287,
        288,
        289,
        290,
        291,
        292,
        293,
        294,
        295,
        296,
        297,
        298,
        299,
        300,
        301,
        302,
        303,
        304,
        305,
        306,
        307,
        308,
        309,
        310,
        311,
        312,
        313,
        314,
        316,
        317,
        318,
        319,
        320,
        321,
        322,
        323,
        324,
        325,
        326,
        327,
        328,
        329,
        330,
        331,
        332,
        333,
        334,
        335,
        336,
        337,
        338,
        339,
        340,
        341,
        342,
        343,
        344,
        345,
        346,
        347,
        348,
        349,
        350,
        351,
        352,
        353,
        354,
        355,
        356,
        357,
        358,
        359,
        360,
        361,
        362,
        364,
        365,
        366,
        367,
        368,
        369,
        370,
        371,
        372,
        373,
        374,
        375,
        376,
        377,
        378,
        379,
        380,
        381,
        382,
        383,
        384,
        385,
        386,
        387,
        388,
        389,
        390,
        391,
        392,
        393,
        394,
        395,
        396,
        397,
        398,
        399,
        400,
        401,
        403,
        405,
        406,
        407,
        409,
        410,
        411,
        412,
        413,
        414
    ],
    "average_idle_rate": 0,
    "idle_rates_by_vehicle": {},
    "total_idle_time": 0,
    "orders_per_hour": 15.285714285714286,
    "active_period_orders_per_hour": 17.833333333333332,
    "system_capacity": 366.8571428571429,
    "active_period_capacity": 428.0,
    "active_period_idle_time": 0,
    "active_period_steps": 360,
    "active_period_idle_rate": 0.050623960249621125,
    "active_period_idle_rates_by_vehicle": {
        "0": 0.05385527686129907,
        "1": 0.07001185991968878,
        "2": 0.04308422148903925,
        "3": 0.026927638430649534,
        "4": 0.021542110744519626,
        "5": 0.04846974917516916,
        "6": 0.04846974917516916,
        "7": 0.03231316611677944,
        "8": 0.06462633223355888,
        "9": 0.026927638430649534,
        "10": 0.0807829152919486,
        "11": 0.07001185991968878,
        "12": 0.010771055372259813,
        "13": 0.0753973876058187,
        "14": 0.0861684429780785
    },
    "orders_per_restaurant": {
        "45": 3,
        "56": 2,
        "78": 1,
        "82": 2,
        "10": 3,
        "76": 2,
        "65": 2,
        "47": 2,
        "62": 1,
        "22": 2,
        "8": 3,
        "98": 2,
        "75": 1,
        "100": 1,
        "48": 1,
        "42": 2,
        "59": 2,
        "7": 1,
        "16": 2,
        "51": 1,
        "46": 2,
        "69": 4,
        "90": 2,
        "88": 3,
        "52": 2,
        "41": 1,
        "80": 3,
        "91": 1,
        "102": 1,
        "66": 1,
        "81": 2,
        "0": 1,
        "27": 1,
        "35": 2,
        "104": 3,
        "103": 1,
        "79": 2,
        "63": 2,
        "71": 1,
        "67": 2,
        "64": 1,
        "60": 1,
        "70": 1,
        "14": 1,
        "77": 1,
        "55": 1,
        "99": 1,
        "101": 2,
        "17": 1,
        "58": 1,
        "105": 1,
        "29": 3,
        "40": 1,
        "38": 2,
        "28": 2,
        "94": 3,
        "30": 1,
        "23": 2,
        "31": 2,
        "89": 1,
        "96": 1,
        "54": 1,
        "3": 1,
        "43": 1,
        "87": 1
    },
    "true_prep_times": [
        13.855665208382105,
        13.216876669742007,
        12.759331754562822,
        13.287731748326937,
        17.15728740390922,
        13.419582697944882,
        13.50777543512853,
        13.871403101272389,
        11.906890891681435,
        13.937593540273191,
        16.98608735018998,
        12.728947510358019,
        11.788228901509783,
        11.58116021248862,
        15.976221633482819,
        13.157345216068084,
        10.155585252365846,
        12.720665019742498,
        13.501247153239014,
        16.118492713638773,
        13.007323594957406,
        14.35369782049409,
        12.985598742658965,
        11.929704602304383,
        13.461970113120401,
        11.763311153195716,
        12.283734487889916,
        12.203801452288914,
        11.50551429127259,
        13.646573106580085,
        13.286107283166665,
        14.005173471999896,
        11.973639286376105,
        14.08607137087165,
        11.768334474525531,
        10.359320748846542,
        12.377167357228366,
        16.02968558096501,
        13.227725422045644,
        14.780168635481914,
        11.527300735332915,
        12.204243039584654,
        9.457091830743252,
        13.439673965513258,
        13.512033773958969,
        13.539815402764859,
        14.507311178744857,
        13.081316551292453,
        13.421345223797289,
        12.07903829456739,
        14.26524248490783,
        14.181215389371829,
        15.195151118782633,
        11.889323931837765,
        15.218768743309553,
        14.042531523594818,
        11.672208053318613,
        12.508927919455289,
        10.561815023609157,
        13.328093774984197,
        15.560184418945184,
        16.07369665564221,
        12.032813229022125,
        11.225139805040243,
        13.827222988328685,
        13.357275217268295,
        13.346165324499324,
        11.487858347821202,
        13.888249106699448,
        14.5372509336339,
        13.942719924257887,
        16.12324748571669,
        13.183229134012052,
        11.682173815890494,
        12.483202710216517,
        11.386347207147338,
        11.75903288024243,
        13.094899887845244,
        16.761645832471743,
        12.965078861173765,
        12.918075768067055,
        16.21720813494207,
        9.946744327761223,
        12.883470653640927,
        12.950442436366984,
        11.568417350331842,
        11.075393828854814,
        13.573227607568384,
        12.252064132318594,
        14.206261329350596,
        12.81150855773268,
        11.591729833830271,
        13.98712451897903,
        12.978212809538576,
        12.20409301253828,
        12.549440745458114,
        11.883455361125996
    ],
    "avg_true_prep_time": 13.14036592313741,
    "max_true_prep_time": 17.15728740390922,
    "order_wait_times": [
        1.1443347916178954,
        0.7831233302579932,
        0.24066824543717757,
        8.712268251673063,
        0.8427125960907809,
        7.5804173020551175,
        0.4922245648714707,
        8.128596898727611,
        8.093109108318565,
        0.062406459726808805,
        2.0139126498100204,
        21.27105248964198,
        9.211771098490217,
        22.41883978751138,
        22.02377836651718,
        16.842654783931916,
        40.844414747634154,
        36.2793349802575,
        26.498752846760986,
        37.88150728636123,
        34.992676405042594,
        36.64630217950591,
        49.014401257341035,
        63.07029539769562,
        61.5380298868796,
        46.236688846804284,
        60.716265512110084,
        57.796198547711086,
        68.49448570872741,
        74.35342689341991,
        69.71389271683333,
        73.9948265280001,
        94.02636071362389,
        73.91392862912835,
        84.23166552547447,
        82.64067925115346,
        97.62283264277164,
        84.97031441903499,
        94.77227457795436,
        103.21983136451809,
        87.47269926466709,
        98.79575696041535,
        102.54290816925675,
        137.56032603448674,
        114.48796622604104,
        109.46018459723514,
        113.49268882125514,
        141.91868344870755,
        132.5786547762027,
        134.9209617054326,
        135.73475751509216,
        125.81878461062817,
        141.80484888121737,
        152.11067606816223,
        151.78123125669043,
        150.95746847640518,
        164.32779194668137,
        130.4910720805447,
        164.43818497639086,
        162.6719062250158,
        168.4398155810548,
        160.9263033443578,
        158.9671867709779,
        155.77486019495976,
        192.17277701167131,
        192.6427247827317,
        156.65383467550066,
        202.5121416521788,
        133.11175089330055,
        200.4627490663661,
        201.0572800757421,
        184.8767525142833,
        195.81677086598796,
        192.3178261841095,
        197.51679728978348,
        207.61365279285266,
        213.24096711975756,
        224.90510011215474,
        175.23835416752826,
        237.03492113882623,
        212.08192423193293,
        233.78279186505793,
        206.05325567223878,
        228.11652934635907,
        229.04955756363302,
        259.43158264966814,
        259.9246061711452,
        201.42677239243162,
        181.7479358676814,
        249.79373867064942,
        255.18849144226732,
        254.40827016616973,
        237.01287548102096,
        259.0217871904614,
        253.7959069874617,
        263.4505592545419,
        265.116544638874
    ],
    "avg_order_wait_time": 125.127675313976,
    "max_order_wait_time": 265.116544638874,
    "total_pickup_times": [
        15,
        14,
        13,
        22,
        18,
        21,
        14,
        22,
        20,
        14,
        19,
        34,
        21,
        34,
        38,
        30,
        51,
        49,
        40,
        54,
        48,
        51,
        62,
        75,
        75,
        58,
        73,
        70,
        80,
        88,
        83,
        88,
        106,
        88,
        96,
        93,
        110,
        101,
        108,
        118,
        99,
        111,
        112,
        151,
        128,
        123,
        128,
        155,
        146,
        147,
        150,
        140,
        157,
        164,
        167,
        165,
        176,
        143,
        175,
        176,
        184,
        177,
        171,
        167,
        206,
        206,
        170,
        214,
        147,
        215,
        215,
        201,
        209,
        204,
        210,
        219,
        225,
        238,
        192,
        250,
        225,
        250,
        216,
        241,
        242,
        271,
        271,
        215,
        194,
        264,
        268,
        266,
        251,
        272,
        266,
        276,
        277
    ],
    "avg_total_pickup_time": 138.2680412371134,
    "max_total_pickup_time": 277,
    "total_driver_wait_time": 14.578864803615769,
    "driver_wait_orders": 5,
    "true_prep_by_restaurant": {
        "45": [
            13.855665208382105,
            16.07369665564221,
            11.075393828854814
        ],
        "56": [
            13.216876669742007,
            13.357275217268295
        ],
        "78": [
            12.759331754562822
        ],
        "10": [
            13.287731748326937,
            13.419582697944882,
            12.549440745458114
        ],
        "76": [
            17.15728740390922
        ],
        "65": [
            13.50777543512853,
            12.918075768067055
        ],
        "47": [
            13.871403101272389,
            13.421345223797289
        ],
        "62": [
            11.906890891681435
        ],
        "22": [
            13.937593540273191,
            14.206261329350596
        ],
        "8": [
            16.98608735018998,
            14.042531523594818,
            16.12324748571669
        ],
        "75": [
            12.728947510358019
        ],
        "100": [
            11.788228901509783
        ],
        "48": [
            11.58116021248862
        ],
        "42": [
            15.976221633482819,
            12.377167357228366
        ],
        "59": [
            13.157345216068084,
            11.682173815890494
        ],
        "7": [
            10.155585252365846
        ],
        "16": [
            12.720665019742498,
            11.487858347821202
        ],
        "51": [
            13.501247153239014
        ],
        "69": [
            16.118492713638773,
            13.439673965513258,
            14.5372509336339,
            13.942719924257887
        ],
        "82": [
            13.007323594957406
        ],
        "90": [
            14.35369782049409,
            11.527300735332915
        ],
        "88": [
            12.985598742658965,
            12.508927919455289,
            12.978212809538576
        ],
        "52": [
            11.929704602304383,
            15.195151118782633
        ],
        "41": [
            13.461970113120401
        ],
        "80": [
            11.763311153195716,
            14.507311178744857,
            16.21720813494207
        ],
        "91": [
            12.283734487889916
        ],
        "102": [
            12.203801452288914
        ],
        "66": [
            11.50551429127259
        ],
        "81": [
            13.646573106580085,
            11.672208053318613
        ],
        "27": [
            14.005173471999896
        ],
        "35": [
            11.973639286376105,
            13.539815402764859
        ],
        "104": [
            14.08607137087165,
            13.888249106699448
        ],
        "103": [
            11.768334474525531
        ],
        "79": [
            10.359320748846542,
            13.227725422045644
        ],
        "46": [
            16.02968558096501
        ],
        "71": [
            14.780168635481914
        ],
        "64": [
            12.204243039584654
        ],
        "60": [
            9.457091830743252
        ],
        "14": [
            13.512033773958969
        ],
        "77": [
            13.081316551292453
        ],
        "55": [
            12.07903829456739
        ],
        "99": [
            14.26524248490783
        ],
        "101": [
            14.181215389371829,
            12.883470653640927
        ],
        "17": [
            11.889323931837765
        ],
        "58": [
            15.218768743309553
        ],
        "98": [
            10.561815023609157
        ],
        "105": [
            13.328093774984197
        ],
        "29": [
            15.560184418945184,
            12.483202710216517,
            12.252064132318594
        ],
        "40": [
            12.032813229022125
        ],
        "38": [
            11.225139805040243,
            13.094899887845244
        ],
        "28": [
            13.827222988328685,
            11.568417350331842
        ],
        "30": [
            13.346165324499324
        ],
        "23": [
            13.183229134012052,
            13.98712451897903
        ],
        "31": [
            11.386347207147338,
            12.965078861173765
        ],
        "89": [
            11.75903288024243
        ],
        "94": [
            16.761645832471743
        ],
        "63": [
            9.946744327761223
        ],
        "96": [
            12.950442436366984
        ],
        "54": [
            13.573227607568384
        ],
        "67": [
            12.81150855773268
        ],
        "3": [
            11.591729833830271
        ],
        "43": [
            12.20409301253828
        ],
        "87": [
            11.883455361125996
        ]
    },
    "driver_wait_by_restaurant": {
        "56": [
            0.2168766697420068
        ],
        "78": [
            4.759331754562822
        ],
        "76": [
            0.15728740390921914
        ],
        "65": [
            3.5077754351285293
        ],
        "22": [
            5.937593540273191
        ]
    },
    "order_wait_by_restaurant": {
        "45": [
            1.1443347916178954,
            160.9263033443578,
            259.9246061711452
        ],
        "56": [
            0.7831233302579932,
            192.6427247827317
        ],
        "78": [
            0.24066824543717757
        ],
        "10": [
            8.712268251673063,
            7.5804173020551175,
            263.4505592545419
        ],
        "76": [
            0.8427125960907809
        ],
        "65": [
            0.4922245648714707,
            212.08192423193293
        ],
        "47": [
            8.128596898727611,
            132.5786547762027
        ],
        "62": [
            8.093109108318565
        ],
        "22": [
            0.062406459726808805,
            249.79373867064942
        ],
        "8": [
            2.0139126498100204,
            150.95746847640518,
            184.8767525142833
        ],
        "75": [
            21.27105248964198
        ],
        "100": [
            9.211771098490217
        ],
        "48": [
            22.41883978751138
        ],
        "42": [
            22.02377836651718,
            97.62283264277164
        ],
        "59": [
            16.842654783931916,
            192.3178261841095
        ],
        "7": [
            40.844414747634154
        ],
        "16": [
            36.2793349802575,
            202.5121416521788
        ],
        "51": [
            26.498752846760986
        ],
        "69": [
            37.88150728636123,
            137.56032603448674,
            200.4627490663661,
            201.0572800757421
        ],
        "82": [
            34.992676405042594
        ],
        "90": [
            36.64630217950591,
            87.47269926466709
        ],
        "88": [
            49.014401257341035,
            130.4910720805447,
            259.0217871904614
        ],
        "52": [
            63.07029539769562,
            141.80484888121737
        ],
        "41": [
            61.5380298868796
        ],
        "80": [
            46.236688846804284,
            113.49268882125514,
            233.78279186505793
        ],
        "91": [
            60.716265512110084
        ],
        "102": [
            57.796198547711086
        ],
        "66": [
            68.49448570872741
        ],
        "81": [
            74.35342689341991,
            164.32779194668137
        ],
        "27": [
            73.9948265280001
        ],
        "35": [
            94.02636071362389,
            109.46018459723514
        ],
        "104": [
            73.91392862912835,
            133.11175089330055
        ],
        "103": [
            84.23166552547447
        ],
        "79": [
            82.64067925115346,
            94.77227457795436
        ],
        "46": [
            84.97031441903499
        ],
        "71": [
            103.21983136451809
        ],
        "64": [
            98.79575696041535
        ],
        "60": [
            102.54290816925675
        ],
        "14": [
            114.48796622604104
        ],
        "77": [
            141.91868344870755
        ],
        "55": [
            134.9209617054326
        ],
        "99": [
            135.73475751509216
        ],
        "101": [
            125.81878461062817,
            228.11652934635907
        ],
        "17": [
            152.11067606816223
        ],
        "58": [
            151.78123125669043
        ],
        "98": [
            164.43818497639086
        ],
        "105": [
            162.6719062250158
        ],
        "29": [
            168.4398155810548,
            197.51679728978348,
            181.7479358676814
        ],
        "40": [
            158.9671867709779
        ],
        "38": [
            155.77486019495976,
            224.90510011215474
        ],
        "28": [
            192.17277701167131,
            259.43158264966814
        ],
        "30": [
            156.65383467550066
        ],
        "23": [
            195.81677086598796,
            237.01287548102096
        ],
        "31": [
            207.61365279285266,
            237.03492113882623
        ],
        "89": [
            213.24096711975756
        ],
        "94": [
            175.23835416752826
        ],
        "63": [
            206.05325567223878
        ],
        "96": [
            229.04955756363302
        ],
        "54": [
            201.42677239243162
        ],
        "67": [
            255.18849144226732
        ],
        "3": [
            254.40827016616973
        ],
        "43": [
            253.7959069874617
        ],
        "87": [
            265.116544638874
        ]
    },
    "total_pickup_by_restaurant": {
        "45": [
            15,
            177,
            271
        ],
        "56": [
            14,
            206
        ],
        "78": [
            13
        ],
        "10": [
            22,
            21,
            276
        ],
        "76": [
            18
        ],
        "65": [
            14,
            225
        ],
        "47": [
            22,
            146
        ],
        "62": [
            20
        ],
        "22": [
            14,
            264
        ],
        "8": [
            19,
            165,
            201
        ],
        "75": [
            34
        ],
        "100": [
            21
        ],
        "48": [
            34
        ],
        "42": [
            38,
            110
        ],
        "59": [
            30,
            204
        ],
        "7": [
            51
        ],
        "16": [
            49,
            214
        ],
        "51": [
            40
        ],
        "69": [
            54,
            151,
            215,
            215
        ],
        "82": [
            48
        ],
        "90": [
            51,
            99
        ],
        "88": [
            62,
            143,
            272
        ],
        "52": [
            75,
            157
        ],
        "41": [
            75
        ],
        "80": [
            58,
            128,
            250
        ],
        "91": [
            73
        ],
        "102": [
            70
        ],
        "66": [
            80
        ],
        "81": [
            88,
            176
        ],
        "27": [
            88
        ],
        "35": [
            106,
            123
        ],
        "104": [
            88,
            147
        ],
        "103": [
            96
        ],
        "79": [
            93,
            108
        ],
        "46": [
            101
        ],
        "71": [
            118
        ],
        "64": [
            111
        ],
        "60": [
            112
        ],
        "14": [
            128
        ],
        "77": [
            155
        ],
        "55": [
            147
        ],
        "99": [
            150
        ],
        "101": [
            140,
            241
        ],
        "17": [
            164
        ],
        "58": [
            167
        ],
        "98": [
            175
        ],
        "105": [
            176
        ],
        "29": [
            184,
            210,
            194
        ],
        "40": [
            171
        ],
        "38": [
            167,
            238
        ],
        "28": [
            206,
            271
        ],
        "30": [
            170
        ],
        "23": [
            209,
            251
        ],
        "31": [
            219,
            250
        ],
        "89": [
            225
        ],
        "94": [
            192
        ],
        "63": [
            216
        ],
        "96": [
            242
        ],
        "54": [
            215
        ],
        "67": [
            268
        ],
        "3": [
            266
        ],
        "43": [
            266
        ],
        "87": [
            277
        ]
    },
    "total_reward": -13249,
    "avg_true_prep_by_restaurant": {
        "45": 13.668251897626376,
        "56": 13.287075943505151,
        "78": 12.759331754562822,
        "10": 13.08558506390998,
        "76": 17.15728740390922,
        "65": 13.212925601597792,
        "47": 13.646374162534839,
        "62": 11.906890891681435,
        "22": 14.071927434811894,
        "8": 15.717288786500495,
        "75": 12.728947510358019,
        "100": 11.788228901509783,
        "48": 11.58116021248862,
        "42": 14.176694495355592,
        "59": 12.419759515979289,
        "7": 10.155585252365846,
        "16": 12.10426168378185,
        "51": 13.501247153239014,
        "69": 14.509534384260954,
        "82": 13.007323594957406,
        "90": 12.940499277913503,
        "88": 12.824246490550943,
        "52": 13.562427860543508,
        "41": 13.461970113120401,
        "80": 14.162610155627547,
        "91": 12.283734487889916,
        "102": 12.203801452288914,
        "66": 11.50551429127259,
        "81": 12.65939057994935,
        "27": 14.005173471999896,
        "35": 12.756727344570482,
        "104": 13.987160238785549,
        "103": 11.768334474525531,
        "79": 11.793523085446093,
        "46": 16.02968558096501,
        "71": 14.780168635481914,
        "64": 12.204243039584654,
        "60": 9.457091830743252,
        "14": 13.512033773958969,
        "77": 13.081316551292453,
        "55": 12.07903829456739,
        "99": 14.26524248490783,
        "101": 13.532343021506378,
        "17": 11.889323931837765,
        "58": 15.218768743309553,
        "98": 10.561815023609157,
        "105": 13.328093774984197,
        "29": 13.431817087160098,
        "40": 12.032813229022125,
        "38": 12.160019846442744,
        "28": 12.697820169330264,
        "30": 13.346165324499324,
        "23": 13.585176826495541,
        "31": 12.175713034160552,
        "89": 11.75903288024243,
        "94": 16.761645832471743,
        "63": 9.946744327761223,
        "96": 12.950442436366984,
        "54": 13.573227607568384,
        "67": 12.81150855773268,
        "3": 11.591729833830271,
        "43": 12.20409301253828,
        "87": 11.883455361125996
    },
    "avg_order_wait_by_restaurant": {
        "45": 140.66508143570695,
        "56": 96.71292405649484,
        "78": 0.24066824543717757,
        "10": 93.24774826942335,
        "76": 0.8427125960907809,
        "65": 106.2870743984022,
        "47": 70.35362583746516,
        "62": 8.093109108318565,
        "22": 124.92807256518812,
        "8": 112.61604454683284,
        "75": 21.27105248964198,
        "100": 9.211771098490217,
        "48": 22.41883978751138,
        "42": 59.82330550464441,
        "59": 104.5802404840207,
        "7": 40.844414747634154,
        "16": 119.39573831621814,
        "51": 26.498752846760986,
        "69": 144.24046561573903,
        "82": 34.992676405042594,
        "90": 62.0595007220865,
        "88": 146.17575350944904,
        "52": 102.43757213945649,
        "41": 61.5380298868796,
        "80": 131.17072317770578,
        "91": 60.716265512110084,
        "102": 57.796198547711086,
        "66": 68.49448570872741,
        "81": 119.34060942005064,
        "27": 73.9948265280001,
        "35": 101.74327265542951,
        "104": 103.51283976121445,
        "103": 84.23166552547447,
        "79": 88.70647691455392,
        "46": 84.97031441903499,
        "71": 103.21983136451809,
        "64": 98.79575696041535,
        "60": 102.54290816925675,
        "14": 114.48796622604104,
        "77": 141.91868344870755,
        "55": 134.9209617054326,
        "99": 135.73475751509216,
        "101": 176.9676569784936,
        "17": 152.11067606816223,
        "58": 151.78123125669043,
        "98": 164.43818497639086,
        "105": 162.6719062250158,
        "29": 182.5681829128399,
        "40": 158.9671867709779,
        "38": 190.33998015355724,
        "28": 225.80217983066973,
        "30": 156.65383467550066,
        "23": 216.41482317350446,
        "31": 222.32428696583946,
        "89": 213.24096711975756,
        "94": 175.23835416752826,
        "63": 206.05325567223878,
        "96": 229.04955756363302,
        "54": 201.42677239243162,
        "67": 255.18849144226732,
        "3": 254.40827016616973,
        "43": 253.7959069874617,
        "87": 265.116544638874
    },
    "avg_total_pickup_by_restaurant": {
        "45": 154.33333333333334,
        "56": 110.0,
        "78": 13.0,
        "10": 106.33333333333333,
        "76": 18.0,
        "65": 119.5,
        "47": 84.0,
        "62": 20.0,
        "22": 139.0,
        "8": 128.33333333333334,
        "75": 34.0,
        "100": 21.0,
        "48": 34.0,
        "42": 74.0,
        "59": 117.0,
        "7": 51.0,
        "16": 131.5,
        "51": 40.0,
        "69": 158.75,
        "82": 48.0,
        "90": 75.0,
        "88": 159.0,
        "52": 116.0,
        "41": 75.0,
        "80": 145.33333333333334,
        "91": 73.0,
        "102": 70.0,
        "66": 80.0,
        "81": 132.0,
        "27": 88.0,
        "35": 114.5,
        "104": 117.5,
        "103": 96.0,
        "79": 100.5,
        "46": 101.0,
        "71": 118.0,
        "64": 111.0,
        "60": 112.0,
        "14": 128.0,
        "77": 155.0,
        "55": 147.0,
        "99": 150.0,
        "101": 190.5,
        "17": 164.0,
        "58": 167.0,
        "98": 175.0,
        "105": 176.0,
        "29": 196.0,
        "40": 171.0,
        "38": 202.5,
        "28": 238.5,
        "30": 170.0,
        "23": 230.0,
        "31": 234.5,
        "89": 225.0,
        "94": 192.0,
        "63": 216.0,
        "96": 242.0,
        "54": 215.0,
        "67": 268.0,
        "3": 266.0,
        "43": 266.0,
        "87": 277.0
    },
    "avg_driver_wait_by_restaurant": {
        "56": 0.2168766697420068,
        "78": 4.759331754562822,
        "76": 0.15728740390921914,
        "65": 3.5077754351285293,
        "22": 5.937593540273191
    },
    "driver_wait_percentage": 4.672897196261682,
    "solver": "rl_aca",
    "seed": 101,
    "timestamp": "20250316_135543",
    "config": {},
    "solver_params": {
        "buffer": 40,
        "max_postponements": 3,
        "max_postpone_time": 10,
        "vehicle_capacity": 3,
        "service_time": 2.0,
        "mean_prep_time": 13
    },
    "env_params": {
        "num_restaurants": 110,
        "num_vehicles": 15,
        "mean_prep_time": 13.0,
        "prep_time_var": 2.0,
        "delivery_window": 40,
        "simulation_duration": 420,
        "cooldown_duration": 0,
        "mean_interarrival_time": 0.2,
        "service_area_dimensions": [
            10.0,
            10.0
        ],
        "downtown_concentration": 0.7,
        "service_time": 0,
        "movement_per_step": 0.16666666666666666,
        "visualize": false,
        "update_interval": 0.01,
        "reposition_idle_vehicles": false,
        "seed": 101,
        "demand_pattern": null
    },
    "on_time_delivery_rate": 3.7383177570093453,
    "percentage_late_orders": 96.26168224299066,
    "avg_delay_late_orders": 128.63106796116506,
    "avg_distance_per_order": 810.1943793197717,
    "total_restaurants_served": 65,
    "avg_orders_per_restaurant": 1.646153846153846,
    "min_restaurant_orders": 1,
    "max_restaurant_orders": 4,
    "top_restaurant_id": 69,
    "top_restaurant_orders": 4,
    "top_restaurants": [
        [
            69,
            4
        ],
        [
            45,
            3
        ],
        [
            10,
            3
        ],
        [
            8,
            3
        ],
        [
            88,
            3
        ]
    ],
    "top_prep_restaurants": [
        [
            76,
            17.15728740390922
        ],
        [
            94,
            16.761645832471743
        ],
        [
            46,
            16.02968558096501
        ],
        [
            8,
            15.717288786500495
        ],
        [
            58,
            15.218768743309553
        ]
    ],
    "top_wait_restaurants": [
        [
            87,
            265.116544638874
        ],
        [
            67,
            255.18849144226732
        ],
        [
            3,
            254.40827016616973
        ],
        [
            43,
            253.7959069874617
        ],
        [
            96,
            229.04955756363302
        ]
    ]
}